py_servicehost/__init__.py
py_servicehost-1.0.1.dist-info/LICENSE
py_servicehost-1.0.1.dist-info/METADATA
py_servicehost-1.0.1.dist-info/WHEEL
py_servicehost-1.0.1.dist-info/top_level.txt
py_servicehost-1.0.1.dist-info/RECORD
